{
  "tracks": [
    {
      "album": {
        "album_type": "ALBUM",
        "artists": [
          {
            "external_urls": {
              "spotify": "https://open.spotify.com/artist/5eAWCfyUhZtHHtBdNk56l1"
            },
            "href": "https://api.spotify.com/v1/artists/5eAWCfyUhZtHHtBdNk56l1",
            "id": "5eAWCfyUhZtHHtBdNk56l1",
            "name": "System Of A Down",
            "type": "artist",
            "uri": "spotify:artist:5eAWCfyUhZtHHtBdNk56l1"
          }
        ],
        "external_urls": {
          "spotify": "https://open.spotify.com/album/6jWde94ln40epKIQCd8XUh"
        },
        "href": "https://api.spotify.com/v1/albums/6jWde94ln40epKIQCd8XUh",
        "id": "6jWde94ln40epKIQCd8XUh",
        "images": [
          {
            "height": 640,
            "url": "https://i.scdn.co/image/3b74b1b2557ec74868bea0dd5c99ed081d32b6f4",
            "width": 640
          },
          {
            "height": 300,
            "url": "https://i.scdn.co/image/2be5b43048eefe03995804863f02f40654469039",
            "width": 300
          },
          {
            "height": 64,
            "url": "https://i.scdn.co/image/de83304fcae7f914c114713fb1297bc6f5b1e902",
            "width": 64
          }
        ],
        "name": "Toxicity",
        "release_date": "2001",
        "release_date_precision": "year",
        "total_tracks": 0,
        "type": "album",
        "uri": "spotify:album:6jWde94ln40epKIQCd8XUh"
      },
      "artists": [
        {
          "external_urls": {
            "spotify": "https://open.spotify.com/artist/5eAWCfyUhZtHHtBdNk56l1"
          },
          "href": "https://api.spotify.com/v1/artists/5eAWCfyUhZtHHtBdNk56l1",
          "id": "5eAWCfyUhZtHHtBdNk56l1",
          "name": "System Of A Down",
          "type": "artist",
          "uri": "spotify:artist:5eAWCfyUhZtHHtBdNk56l1"
        }
      ],
      "disc_number": 1,
      "duration_ms": 240106,
      "explicit": false,
      "external_ids": {
        "isrc": "USSM10107258"
      },
      "external_urls": {
        "spotify": "https://open.spotify.com/track/1B5Y9I5wPfvD3C2A81A36C"
      },
      "href": "https://api.spotify.com/v1/tracks/1B5Y9I5wPfvD3C2A81A36C",
      "id": "1B5Y9I5wPfvD3C2A81A36C",
      "is_local": false,
      "is_playable": true,
      "name": "Forest",
      "popularity": 59,
      "preview_url": "https://p.scdn.co/mp3-preview/7a9250e1e82a52cbf71a18545499a8f6adf3d468?cid=774b29d4f13844c495f206cafdad9c86",
      "track_number": 8,
      "type": "track",
      "uri": "spotify:track:1B5Y9I5wPfvD3C2A81A36C"
    },
    {
      "album": {
        "album_type": "ALBUM",
        "artists": [
          {
            "external_urls": {
              "spotify": "https://open.spotify.com/artist/4S2yOnmsWW97dT87yVoaSZ"
            },
            "href": "https://api.spotify.com/v1/artists/4S2yOnmsWW97dT87yVoaSZ",
            "id": "4S2yOnmsWW97dT87yVoaSZ",
            "name": "NOFX",
            "type": "artist",
            "uri": "spotify:artist:4S2yOnmsWW97dT87yVoaSZ"
          }
        ],
        "external_urls": {
          "spotify": "https://open.spotify.com/album/579FRQBE6RnFZXn6dG0DeV"
        },
        "href": "https://api.spotify.com/v1/albums/579FRQBE6RnFZXn6dG0DeV",
        "id": "579FRQBE6RnFZXn6dG0DeV",
        "images": [
          {
            "height": 640,
            "url": "https://i.scdn.co/image/00709f22517303da79aca3b03563bd8de14eaf0a",
            "width": 640
          },
          {
            "height": 300,
            "url": "https://i.scdn.co/image/3a49cb4f47b979cd8798ad8ea2708de5c196b689",
            "width": 300
          },
          {
            "height": 64,
            "url": "https://i.scdn.co/image/a3ab06f33d973d58725cfb0fbf5bb0b96ab08007",
            "width": 64
          }
        ],
        "name": "War on Errorism",
        "release_date": "2003-08-19",
        "release_date_precision": "day",
        "total_tracks": 0,
        "type": "album",
        "uri": "spotify:album:579FRQBE6RnFZXn6dG0DeV"
      },
      "artists": [
        {
          "external_urls": {
            "spotify": "https://open.spotify.com/artist/4S2yOnmsWW97dT87yVoaSZ"
          },
          "href": "https://api.spotify.com/v1/artists/4S2yOnmsWW97dT87yVoaSZ",
          "id": "4S2yOnmsWW97dT87yVoaSZ",
          "name": "NOFX",
          "type": "artist",
          "uri": "spotify:artist:4S2yOnmsWW97dT87yVoaSZ"
        }
      ],
      "disc_number": 1,
      "duration_ms": 145466,
      "explicit": false,
      "external_ids": {
        "isrc": "USFW40465703"
      },
      "external_urls": {
        "spotify": "https://open.spotify.com/track/180jsAPdTdsP31LyuYdGan"
      },
      "href": "https://api.spotify.com/v1/tracks/180jsAPdTdsP31LyuYdGan",
      "id": "180jsAPdTdsP31LyuYdGan",
      "is_local": false,
      "is_playable": true,
      "name": "Franco Un-American",
      "popularity": 51,
      "preview_url": "https://p.scdn.co/mp3-preview/8db8ee9ce418fe692875e8daa3ad948a0fe74c99?cid=774b29d4f13844c495f206cafdad9c86",
      "track_number": 3,
      "type": "track",
      "uri": "spotify:track:180jsAPdTdsP31LyuYdGan"
    },
    {
      "album": {
        "album_type": "ALBUM",
        "artists": [
          {
            "external_urls": {
              "spotify": "https://open.spotify.com/artist/6GkJh85o22LfD2vgL9DP6f"
            },
            "href": "https://api.spotify.com/v1/artists/6GkJh85o22LfD2vgL9DP6f",
            "id": "6GkJh85o22LfD2vgL9DP6f",
            "name": "Dirty Heads",
            "type": "artist",
            "uri": "spotify:artist:6GkJh85o22LfD2vgL9DP6f"
          }
        ],
        "external_urls": {
          "spotify": "https://open.spotify.com/album/7xR5BJoQg0x0bHac8GMipk"
        },
        "href": "https://api.spotify.com/v1/albums/7xR5BJoQg0x0bHac8GMipk",
        "id": "7xR5BJoQg0x0bHac8GMipk",
        "images": [
          {
            "height": 640,
            "url": "https://i.scdn.co/image/aa389ec974637870c7e4f33318b08744fdeb0ed9",
            "width": 640
          },
          {
            "height": 300,
            "url": "https://i.scdn.co/image/8a849d1911dd9537f7a3d2d5a1e89c1c486b2930",
            "width": 300
          },
          {
            "height": 64,
            "url": "https://i.scdn.co/image/55b589786a93ebc543120b6c9955bc4bf6cac43d",
            "width": 64
          }
        ],
        "name": "Vacation",
        "release_date": "2017-06-30",
        "release_date_precision": "day",
        "total_tracks": 0,
        "type": "album",
        "uri": "spotify:album:7xR5BJoQg0x0bHac8GMipk"
      },
      "artists": [
        {
          "external_urls": {
            "spotify": "https://open.spotify.com/artist/6GkJh85o22LfD2vgL9DP6f"
          },
          "href": "https://api.spotify.com/v1/artists/6GkJh85o22LfD2vgL9DP6f",
          "id": "6GkJh85o22LfD2vgL9DP6f",
          "name": "Dirty Heads",
          "type": "artist",
          "uri": "spotify:artist:6GkJh85o22LfD2vgL9DP6f"
        }
      ],
      "disc_number": 1,
      "duration_ms": 209142,
      "explicit": false,
      "external_ids": {
        "isrc": "USDPK1700118"
      },
      "external_urls": {
        "spotify": "https://open.spotify.com/track/7cdy4PbCdDZZNjyxoZyE0c"
      },
      "href": "https://api.spotify.com/v1/tracks/7cdy4PbCdDZZNjyxoZyE0c",
      "id": "7cdy4PbCdDZZNjyxoZyE0c",
      "is_local": false,
      "is_playable": true,
      "name": "Vacation",
      "popularity": 66,
      "preview_url": "https://p.scdn.co/mp3-preview/bb0ede798b01af57eaf1c54260bf4fec89f14a04?cid=774b29d4f13844c495f206cafdad9c86",
      "track_number": 1,
      "type": "track",
      "uri": "spotify:track:7cdy4PbCdDZZNjyxoZyE0c"
    },
    {
      "album": {
        "album_type": "ALBUM",
        "artists": [
          {
            "external_urls": {
              "spotify": "https://open.spotify.com/artist/2xiIXseIJcq3nG7C8fHeBj"
            },
            "href": "https://api.spotify.com/v1/artists/2xiIXseIJcq3nG7C8fHeBj",
            "id": "2xiIXseIJcq3nG7C8fHeBj",
            "name": "Three Days Grace",
            "type": "artist",
            "uri": "spotify:artist:2xiIXseIJcq3nG7C8fHeBj"
          }
        ],
        "external_urls": {
          "spotify": "https://open.spotify.com/album/4ZDwEvXIKxWdwhAQK8ndBU"
        },
        "href": "https://api.spotify.com/v1/albums/4ZDwEvXIKxWdwhAQK8ndBU",
        "id": "4ZDwEvXIKxWdwhAQK8ndBU",
        "images": [
          {
            "height": 640,
            "url": "https://i.scdn.co/image/fdbdf54c69e505c617b128d19e670d753573add6",
            "width": 640
          },
          {
            "height": 300,
            "url": "https://i.scdn.co/image/2e3b58d63ec69a8ebc289006c359db5bff97c907",
            "width": 300
          },
          {
            "height": 64,
            "url": "https://i.scdn.co/image/84620e49624132a0757c5e9ed330568c586982d9",
            "width": 64
          }
        ],
        "name": "One-X",
        "release_date": "2006-06-25",
        "release_date_precision": "day",
        "total_tracks": 0,
        "type": "album",
        "uri": "spotify:album:4ZDwEvXIKxWdwhAQK8ndBU"
      },
      "artists": [
        {
          "external_urls": {
            "spotify": "https://open.spotify.com/artist/2xiIXseIJcq3nG7C8fHeBj"
          },
          "href": "https://api.spotify.com/v1/artists/2xiIXseIJcq3nG7C8fHeBj",
          "id": "2xiIXseIJcq3nG7C8fHeBj",
          "name": "Three Days Grace",
          "type": "artist",
          "uri": "spotify:artist:2xiIXseIJcq3nG7C8fHeBj"
        }
      ],
      "disc_number": 1,
      "duration_ms": 209333,
      "explicit": false,
      "external_ids": {
        "isrc": "USJI10600166"
      },
      "external_urls": {
        "spotify": "https://open.spotify.com/track/3HE50TVRquwXe9yv2HFoNL"
      },
      "href": "https://api.spotify.com/v1/tracks/3HE50TVRquwXe9yv2HFoNL",
      "id": "3HE50TVRquwXe9yv2HFoNL",
      "is_local": false,
      "is_playable": true,
      "name": "Never Too Late",
      "popularity": 69,
      "preview_url": "https://p.scdn.co/mp3-preview/d4674d5eedb8eee7f115838954cbd0016cc0e701?cid=774b29d4f13844c495f206cafdad9c86",
      "track_number": 4,
      "type": "track",
      "uri": "spotify:track:3HE50TVRquwXe9yv2HFoNL"
    },
    {
      "album": {
        "album_type": "ALBUM",
        "artists": [
          {
            "external_urls": {
              "spotify": "https://open.spotify.com/artist/0jJNGWrpjGIHUdTTJiIYeB"
            },
            "href": "https://api.spotify.com/v1/artists/0jJNGWrpjGIHUdTTJiIYeB",
            "id": "0jJNGWrpjGIHUdTTJiIYeB",
            "name": "The Wallflowers",
            "type": "artist",
            "uri": "spotify:artist:0jJNGWrpjGIHUdTTJiIYeB"
          }
        ],
        "external_urls": {
          "spotify": "https://open.spotify.com/album/2BOlaNQt6WJ1HO5pQcKHGh"
        },
        "href": "https://api.spotify.com/v1/albums/2BOlaNQt6WJ1HO5pQcKHGh",
        "id": "2BOlaNQt6WJ1HO5pQcKHGh",
        "images": [
          {
            "height": 635,
            "url": "https://i.scdn.co/image/a68dd1fbad04044d4415ed1f4ea4a9a676856b0b",
            "width": 640
          },
          {
            "height": 297,
            "url": "https://i.scdn.co/image/b5814bdc0de085085ef60585589d66865efeb88d",
            "width": 300
          },
          {
            "height": 63,
            "url": "https://i.scdn.co/image/fc119a1fd167d75277c14aa4411e6bee89ea7d98",
            "width": 64
          }
        ],
        "name": "Bringing Down The Horse",
        "release_date": "1996-01-01",
        "release_date_precision": "day",
        "total_tracks": 0,
        "type": "album",
        "uri": "spotify:album:2BOlaNQt6WJ1HO5pQcKHGh"
      },
      "artists": [
        {
          "external_urls": {
            "spotify": "https://open.spotify.com/artist/0jJNGWrpjGIHUdTTJiIYeB"
          },
          "href": "https://api.spotify.com/v1/artists/0jJNGWrpjGIHUdTTJiIYeB",
          "id": "0jJNGWrpjGIHUdTTJiIYeB",
          "name": "The Wallflowers",
          "type": "artist",
          "uri": "spotify:artist:0jJNGWrpjGIHUdTTJiIYeB"
        }
      ],
      "disc_number": 1,
      "duration_ms": 337400,
      "explicit": false,
      "external_ids": {
        "isrc": "USIR19600463"
      },
      "external_urls": {
        "spotify": "https://open.spotify.com/track/1qEyqHR1xsj2MC4Qy0dsaI"
      },
      "href": "https://api.spotify.com/v1/tracks/1qEyqHR1xsj2MC4Qy0dsaI",
      "id": "1qEyqHR1xsj2MC4Qy0dsaI",
      "is_local": false,
      "is_playable": true,
      "name": "6th Avenue Heartache",
      "popularity": 57,
      "preview_url": null,
      "track_number": 2,
      "type": "track",
      "uri": "spotify:track:1qEyqHR1xsj2MC4Qy0dsaI"
    },
    {
      "album": {
        "album_type": "ALBUM",
        "artists": [
          {
            "external_urls": {
              "spotify": "https://open.spotify.com/artist/5eAWCfyUhZtHHtBdNk56l1"
            },
            "href": "https://api.spotify.com/v1/artists/5eAWCfyUhZtHHtBdNk56l1",
            "id": "5eAWCfyUhZtHHtBdNk56l1",
            "name": "System Of A Down",
            "type": "artist",
            "uri": "spotify:artist:5eAWCfyUhZtHHtBdNk56l1"
          }
        ],
        "external_urls": {
          "spotify": "https://open.spotify.com/album/0cn6MHyx4YuZauaB7Pb66o"
        },
        "href": "https://api.spotify.com/v1/albums/0cn6MHyx4YuZauaB7Pb66o",
        "id": "0cn6MHyx4YuZauaB7Pb66o",
        "images": [
          {
            "height": 640,
            "url": "https://i.scdn.co/image/66eb75e0f3a8a91822ba7154e4b41066e63e51f2",
            "width": 640
          },
          {
            "height": 300,
            "url": "https://i.scdn.co/image/df6b8f413c14579d752ebbc37dd6bfd7852b7611",
            "width": 300
          },
          {
            "height": 64,
            "url": "https://i.scdn.co/image/1a0bf07e652bf53bcb8896c424ba363ceec8b9bd",
            "width": 64
          }
        ],
        "name": "Mezmerize",
        "release_date": "2005-05-17",
        "release_date_precision": "day",
        "total_tracks": 0,
        "type": "album",
        "uri": "spotify:album:0cn6MHyx4YuZauaB7Pb66o"
      },
      "artists": [
        {
          "external_urls": {
            "spotify": "https://open.spotify.com/artist/5eAWCfyUhZtHHtBdNk56l1"
          },
          "href": "https://api.spotify.com/v1/artists/5eAWCfyUhZtHHtBdNk56l1",
          "id": "5eAWCfyUhZtHHtBdNk56l1",
          "name": "System Of A Down",
          "type": "artist",
          "uri": "spotify:artist:5eAWCfyUhZtHHtBdNk56l1"
        }
      ],
      "disc_number": 1,
      "duration_ms": 320693,
      "explicit": false,
      "external_ids": {
        "isrc": "USSM10501587"
      },
      "external_urls": {
        "spotify": "https://open.spotify.com/track/0GrHWVTDsaWcD4nrCGr7VE"
      },
      "href": "https://api.spotify.com/v1/tracks/0GrHWVTDsaWcD4nrCGr7VE",
      "id": "0GrHWVTDsaWcD4nrCGr7VE",
      "is_local": false,
      "is_playable": true,
      "name": "Lost In Hollywood",
      "popularity": 65,
      "preview_url": "https://p.scdn.co/mp3-preview/bdaad68f6bb8ed361d0c2d8e9bc127f696f480d9?cid=774b29d4f13844c495f206cafdad9c86",
      "track_number": 11,
      "type": "track",
      "uri": "spotify:track:0GrHWVTDsaWcD4nrCGr7VE"
    },
    {
      "album": {
        "album_type": "ALBUM",
        "artists": [
          {
            "external_urls": {
              "spotify": "https://open.spotify.com/artist/7JDSHlDdVTo7aZKdQZ53Vf"
            },
            "href": "https://api.spotify.com/v1/artists/7JDSHlDdVTo7aZKdQZ53Vf",
            "id": "7JDSHlDdVTo7aZKdQZ53Vf",
            "name": "Static-X",
            "type": "artist",
            "uri": "spotify:artist:7JDSHlDdVTo7aZKdQZ53Vf"
          }
        ],
        "external_urls": {
          "spotify": "https://open.spotify.com/album/2WRLwr5MIIXr9gAWOOQ6J5"
        },
        "href": "https://api.spotify.com/v1/albums/2WRLwr5MIIXr9gAWOOQ6J5",
        "id": "2WRLwr5MIIXr9gAWOOQ6J5",
        "images": [
          {
            "height": 640,
            "url": "https://i.scdn.co/image/a4ec9d12ba79c84a1426efeefa23a18ddc06573d",
            "width": 640
          },
          {
            "height": 300,
            "url": "https://i.scdn.co/image/1e792cac16ab46bfb211f3d1b906fa3eebf21b55",
            "width": 300
          },
          {
            "height": 64,
            "url": "https://i.scdn.co/image/16c300820777be4407b971ba59ad6f8678133a94",
            "width": 64
          }
        ],
        "name": "Wisconsin Death Trip",
        "release_date": "1999-03-19",
        "release_date_precision": "day",
        "total_tracks": 0,
        "type": "album",
        "uri": "spotify:album:2WRLwr5MIIXr9gAWOOQ6J5"
      },
      "artists": [
        {
          "external_urls": {
            "spotify": "https://open.spotify.com/artist/7JDSHlDdVTo7aZKdQZ53Vf"
          },
          "href": "https://api.spotify.com/v1/artists/7JDSHlDdVTo7aZKdQZ53Vf",
          "id": "7JDSHlDdVTo7aZKdQZ53Vf",
          "name": "Static-X",
          "type": "artist",
          "uri": "spotify:artist:7JDSHlDdVTo7aZKdQZ53Vf"
        }
      ],
      "disc_number": 1,
      "duration_ms": 154906,
      "explicit": false,
      "external_ids": {
        "isrc": "USWB19800988"
      },
      "external_urls": {
        "spotify": "https://open.spotify.com/track/6O7pihLJgeqxUnG7u9oYL2"
      },
      "href": "https://api.spotify.com/v1/tracks/6O7pihLJgeqxUnG7u9oYL2",
      "id": "6O7pihLJgeqxUnG7u9oYL2",
      "is_local": false,
      "is_playable": true,
      "name": "Push It",
      "popularity": 63,
      "preview_url": "https://p.scdn.co/mp3-preview/94e1bfa67c754d478e982bf2ad66b8ecce5c4df0?cid=774b29d4f13844c495f206cafdad9c86",
      "track_number": 1,
      "type": "track",
      "uri": "spotify:track:6O7pihLJgeqxUnG7u9oYL2"
    },
    {
      "album": {
        "album_type": "ALBUM",
        "artists": [
          {
            "external_urls": {
              "spotify": "https://open.spotify.com/artist/4e5V1Q2dKCzbLVMQ8qbTn6"
            },
            "href": "https://api.spotify.com/v1/artists/4e5V1Q2dKCzbLVMQ8qbTn6",
            "id": "4e5V1Q2dKCzbLVMQ8qbTn6",
            "name": "Collective Soul",
            "type": "artist",
            "uri": "spotify:artist:4e5V1Q2dKCzbLVMQ8qbTn6"
          }
        ],
        "external_urls": {
          "spotify": "https://open.spotify.com/album/3uSVy9q97sAzd5UE0dMdOT"
        },
        "href": "https://api.spotify.com/v1/albums/3uSVy9q97sAzd5UE0dMdOT",
        "id": "3uSVy9q97sAzd5UE0dMdOT",
        "images": [
          {
            "height": 640,
            "url": "https://i.scdn.co/image/b19740a70ab1c418b74f2cb721f2c3f63ef1fa89",
            "width": 640
          },
          {
            "height": 300,
            "url": "https://i.scdn.co/image/95de728fe07db7f8f87ebc9fd929f2043bcd83f9",
            "width": 300
          },
          {
            "height": 64,
            "url": "https://i.scdn.co/image/e18f3a5676a4e1a8efb74f075f7bddfc688f1dd3",
            "width": 64
          }
        ],
        "name": "Hints, Allegations & Things Left Unsaid",
        "release_date": "1994-03-29",
        "release_date_precision": "day",
        "total_tracks": 0,
        "type": "album",
        "uri": "spotify:album:3uSVy9q97sAzd5UE0dMdOT"
      },
      "artists": [
        {
          "external_urls": {
            "spotify": "https://open.spotify.com/artist/4e5V1Q2dKCzbLVMQ8qbTn6"
          },
          "href": "https://api.spotify.com/v1/artists/4e5V1Q2dKCzbLVMQ8qbTn6",
          "id": "4e5V1Q2dKCzbLVMQ8qbTn6",
          "name": "Collective Soul",
          "type": "artist",
          "uri": "spotify:artist:4e5V1Q2dKCzbLVMQ8qbTn6"
        }
      ],
      "disc_number": 1,
      "duration_ms": 306040,
      "explicit": false,
      "external_ids": {
        "isrc": "USAT29300016"
      },
      "external_urls": {
        "spotify": "https://open.spotify.com/track/1HZ3cUZUw5htSFmah1V8Ko"
      },
      "href": "https://api.spotify.com/v1/tracks/1HZ3cUZUw5htSFmah1V8Ko",
      "id": "1HZ3cUZUw5htSFmah1V8Ko",
      "is_local": false,
      "is_playable": true,
      "name": "Shine",
      "popularity": 66,
      "preview_url": "https://p.scdn.co/mp3-preview/df7721724d7268d502f2260424035e42390c748a?cid=774b29d4f13844c495f206cafdad9c86",
      "track_number": 1,
      "type": "track",
      "uri": "spotify:track:1HZ3cUZUw5htSFmah1V8Ko"
    },
    {
      "album": {
        "album_type": "ALBUM",
        "artists": [
          {
            "external_urls": {
              "spotify": "https://open.spotify.com/artist/7jgZFR40bWjwOrRCOZFB02"
            },
            "href": "https://api.spotify.com/v1/artists/7jgZFR40bWjwOrRCOZFB02",
            "id": "7jgZFR40bWjwOrRCOZFB02",
            "name": "Tribal Seeds",
            "type": "artist",
            "uri": "spotify:artist:7jgZFR40bWjwOrRCOZFB02"
          }
        ],
        "external_urls": {
          "spotify": "https://open.spotify.com/album/06tfjVe3cjac8Z8ZEBfUyF"
        },
        "href": "https://api.spotify.com/v1/albums/06tfjVe3cjac8Z8ZEBfUyF",
        "id": "06tfjVe3cjac8Z8ZEBfUyF",
        "images": [
          {
            "height": 640,
            "url": "https://i.scdn.co/image/94b99cd2efe96cbfbecad90c06ba0c203ddd4013",
            "width": 640
          },
          {
            "height": 300,
            "url": "https://i.scdn.co/image/580cc6e795bd8b0cd42aab3760dd49fcddf46380",
            "width": 300
          },
          {
            "height": 64,
            "url": "https://i.scdn.co/image/ec62c760003e7f553ed19309dfabf8583b1d46ed",
            "width": 64
          }
        ],
        "name": "The Harvest",
        "release_date": "2009-05-26",
        "release_date_precision": "day",
        "total_tracks": 0,
        "type": "album",
        "uri": "spotify:album:06tfjVe3cjac8Z8ZEBfUyF"
      },
      "artists": [
        {
          "external_urls": {
            "spotify": "https://open.spotify.com/artist/7jgZFR40bWjwOrRCOZFB02"
          },
          "href": "https://api.spotify.com/v1/artists/7jgZFR40bWjwOrRCOZFB02",
          "id": "7jgZFR40bWjwOrRCOZFB02",
          "name": "Tribal Seeds",
          "type": "artist",
          "uri": "spotify:artist:7jgZFR40bWjwOrRCOZFB02"
        }
      ],
      "disc_number": 1,
      "duration_ms": 297453,
      "explicit": false,
      "external_ids": {
        "isrc": "ushm20928946"
      },
      "external_urls": {
        "spotify": "https://open.spotify.com/track/0d5kLB4iMx2208UwieUzNa"
      },
      "href": "https://api.spotify.com/v1/tracks/0d5kLB4iMx2208UwieUzNa",
      "id": "0d5kLB4iMx2208UwieUzNa",
      "is_local": false,
      "is_playable": true,
      "name": "The Garden",
      "popularity": 54,
      "preview_url": "https://p.scdn.co/mp3-preview/24db7dba6a2841639e898ba9a20013566c3e6805?cid=774b29d4f13844c495f206cafdad9c86",
      "track_number": 1,
      "type": "track",
      "uri": "spotify:track:0d5kLB4iMx2208UwieUzNa"
    },
    {
      "album": {
        "album_type": "ALBUM",
        "artists": [
          {
            "external_urls": {
              "spotify": "https://open.spotify.com/artist/6eoJpTIlcuxJNjV5fDzDJH"
            },
            "href": "https://api.spotify.com/v1/artists/6eoJpTIlcuxJNjV5fDzDJH",
            "id": "6eoJpTIlcuxJNjV5fDzDJH",
            "name": "Live",
            "type": "artist",
            "uri": "spotify:artist:6eoJpTIlcuxJNjV5fDzDJH"
          }
        ],
        "external_urls": {
          "spotify": "https://open.spotify.com/album/1PsHpu1IZBCuZ3bXD2CFSd"
        },
        "href": "https://api.spotify.com/v1/albums/1PsHpu1IZBCuZ3bXD2CFSd",
        "id": "1PsHpu1IZBCuZ3bXD2CFSd",
        "images": [
          {
            "height": 637,
            "url": "https://i.scdn.co/image/8ff53ad720b8f792b4f53786cd24cf037bc55fbe",
            "width": 640
          },
          {
            "height": 299,
            "url": "https://i.scdn.co/image/03e80c692570f7ce769d44c4a0a5ac5752e73b4f",
            "width": 300
          },
          {
            "height": 64,
            "url": "https://i.scdn.co/image/7d11bbc541c2d001f6d47431412befbe766f37bf",
            "width": 64
          }
        ],
        "name": "The Distance To Here",
        "release_date": "1999-01-01",
        "release_date_precision": "day",
        "total_tracks": 0,
        "type": "album",
        "uri": "spotify:album:1PsHpu1IZBCuZ3bXD2CFSd"
      },
      "artists": [
        {
          "external_urls": {
            "spotify": "https://open.spotify.com/artist/6eoJpTIlcuxJNjV5fDzDJH"
          },
          "href": "https://api.spotify.com/v1/artists/6eoJpTIlcuxJNjV5fDzDJH",
          "id": "6eoJpTIlcuxJNjV5fDzDJH",
          "name": "Live",
          "type": "artist",
          "uri": "spotify:artist:6eoJpTIlcuxJNjV5fDzDJH"
        }
      ],
      "disc_number": 1,
      "duration_ms": 264160,
      "explicit": false,
      "external_ids": {
        "isrc": "USMC19959412"
      },
      "external_urls": {
        "spotify": "https://open.spotify.com/track/6FPnecQDKOWSAKDKBAZ7ZG"
      },
      "href": "https://api.spotify.com/v1/tracks/6FPnecQDKOWSAKDKBAZ7ZG",
      "id": "6FPnecQDKOWSAKDKBAZ7ZG",
      "is_local": false,
      "is_playable": true,
      "name": "The Dolphin's Cry",
      "popularity": 56,
      "preview_url": null,
      "track_number": 1,
      "type": "track",
      "uri": "spotify:track:6FPnecQDKOWSAKDKBAZ7ZG"
    },
    {
      "album": {
        "album_type": "ALBUM",
        "artists": [
          {
            "external_urls": {
              "spotify": "https://open.spotify.com/artist/5t28BP42x2axFnqOOMg3CM"
            },
            "href": "https://api.spotify.com/v1/artists/5t28BP42x2axFnqOOMg3CM",
            "id": "5t28BP42x2axFnqOOMg3CM",
            "name": "Five Finger Death Punch",
            "type": "artist",
            "uri": "spotify:artist:5t28BP42x2axFnqOOMg3CM"
          }
        ],
        "external_urls": {
          "spotify": "https://open.spotify.com/album/3Ey9TgEz0LdFKFKKftpkN1"
        },
        "href": "https://api.spotify.com/v1/albums/3Ey9TgEz0LdFKFKKftpkN1",
        "id": "3Ey9TgEz0LdFKFKKftpkN1",
        "images": [
          {
            "height": 640,
            "url": "https://i.scdn.co/image/2573ee566184ef1d507ac8760f6bfb6f5d4a94af",
            "width": 640
          },
          {
            "height": 300,
            "url": "https://i.scdn.co/image/c59927b1e4a6123cd27a14988be49565450e7133",
            "width": 300
          },
          {
            "height": 64,
            "url": "https://i.scdn.co/image/414df9b218c53a5c77eee283a61f9a8c9f1f504b",
            "width": 64
          }
        ],
        "name": "The Wrong Side of Heaven and the Righteous Side of Hell, Vol. 1",
        "release_date": "2013-07-30",
        "release_date_precision": "day",
        "total_tracks": 0,
        "type": "album",
        "uri": "spotify:album:3Ey9TgEz0LdFKFKKftpkN1"
      },
      "artists": [
        {
          "external_urls": {
            "spotify": "https://open.spotify.com/artist/5t28BP42x2axFnqOOMg3CM"
          },
          "href": "https://api.spotify.com/v1/artists/5t28BP42x2axFnqOOMg3CM",
          "id": "5t28BP42x2axFnqOOMg3CM",
          "name": "Five Finger Death Punch",
          "type": "artist",
          "uri": "spotify:artist:5t28BP42x2axFnqOOMg3CM"
        }
      ],
      "disc_number": 1,
      "duration_ms": 271000,
      "explicit": true,
      "external_ids": {
        "isrc": "US5Z51300299"
      },
      "external_urls": {
        "spotify": "https://open.spotify.com/track/6xgO2ICtpT8jDcYvVsCKIB"
      },
      "href": "https://api.spotify.com/v1/tracks/6xgO2ICtpT8jDcYvVsCKIB",
      "id": "6xgO2ICtpT8jDcYvVsCKIB",
      "is_local": false,
      "is_playable": true,
      "name": "Wrong Side of Heaven",
      "popularity": 67,
      "preview_url": "https://p.scdn.co/mp3-preview/89ded795cf02ae31b5324f1e0dcf9859ea89d7f6?cid=774b29d4f13844c495f206cafdad9c86",
      "track_number": 4,
      "type": "track",
      "uri": "spotify:track:6xgO2ICtpT8jDcYvVsCKIB"
    },
    {
      "album": {
        "album_type": "ALBUM",
        "artists": [
          {
            "external_urls": {
              "spotify": "https://open.spotify.com/artist/4UXqAaa6dQYAk18Lv7PEgX"
            },
            "href": "https://api.spotify.com/v1/artists/4UXqAaa6dQYAk18Lv7PEgX",
            "id": "4UXqAaa6dQYAk18Lv7PEgX",
            "name": "Fall Out Boy",
            "type": "artist",
            "uri": "spotify:artist:4UXqAaa6dQYAk18Lv7PEgX"
          }
        ],
        "external_urls": {
          "spotify": "https://open.spotify.com/album/022DrG7Wp2PSCwzuD0bSzT"
        },
        "href": "https://api.spotify.com/v1/albums/022DrG7Wp2PSCwzuD0bSzT",
        "id": "022DrG7Wp2PSCwzuD0bSzT",
        "images": [
          {
            "height": 640,
            "url": "https://i.scdn.co/image/e60f28b3f68f9cc63fc7df1ff04f934888fa2081",
            "width": 640
          },
          {
            "height": 300,
            "url": "https://i.scdn.co/image/51882490356829af5ffe0d45a5a73a4d9b2d07ed",
            "width": 300
          },
          {
            "height": 64,
            "url": "https://i.scdn.co/image/84075ee69250e20b04129634714b3f4e8fed395b",
            "width": 64
          }
        ],
        "name": "American Beauty/American Psycho",
        "release_date": "2015-01-20",
        "release_date_precision": "day",
        "total_tracks": 0,
        "type": "album",
        "uri": "spotify:album:022DrG7Wp2PSCwzuD0bSzT"
      },
      "artists": [
        {
          "external_urls": {
            "spotify": "https://open.spotify.com/artist/4UXqAaa6dQYAk18Lv7PEgX"
          },
          "href": "https://api.spotify.com/v1/artists/4UXqAaa6dQYAk18Lv7PEgX",
          "id": "4UXqAaa6dQYAk18Lv7PEgX",
          "name": "Fall Out Boy",
          "type": "artist",
          "uri": "spotify:artist:4UXqAaa6dQYAk18Lv7PEgX"
        }
      ],
      "disc_number": 1,
      "duration_ms": 211573,
      "explicit": false,
      "external_ids": {
        "isrc": "USUM71417734"
      },
      "external_urls": {
        "spotify": "https://open.spotify.com/track/5PUawWFG1oIS2NwEcyHaCr"
      },
      "href": "https://api.spotify.com/v1/tracks/5PUawWFG1oIS2NwEcyHaCr",
      "id": "5PUawWFG1oIS2NwEcyHaCr",
      "is_local": false,
      "is_playable": true,
      "name": "Uma Thurman",
      "popularity": 71,
      "preview_url": null,
      "track_number": 5,
      "type": "track",
      "uri": "spotify:track:5PUawWFG1oIS2NwEcyHaCr"
    }
  ],
  "seeds": [
    {
      "initialPoolSize": 250,
      "afterFilteringSize": 3,
      "afterRelinkingSize": 3,
      "id": "6TcnmlCSxihzWOQJ8k0rNS",
      "type": "ARTIST",
      "href": "https://api.spotify.com/v1/artists/6TcnmlCSxihzWOQJ8k0rNS"
    },
    {
      "initialPoolSize": 250,
      "afterFilteringSize": 3,
      "afterRelinkingSize": 3,
      "id": "0EdvGhlC1FkGItLOWQzG4J",
      "type": "ARTIST",
      "href": "https://api.spotify.com/v1/artists/0EdvGhlC1FkGItLOWQzG4J"
    },
    {
      "initialPoolSize": 250,
      "afterFilteringSize": 2,
      "afterRelinkingSize": 2,
      "id": "7oPftvlwr6VrsViSDV7fJY",
      "type": "ARTIST",
      "href": "https://api.spotify.com/v1/artists/7oPftvlwr6VrsViSDV7fJY"
    },
    {
      "initialPoolSize": 250,
      "afterFilteringSize": 4,
      "afterRelinkingSize": 4,
      "id": "5eAWCfyUhZtHHtBdNk56l1",
      "type": "ARTIST",
      "href": "https://api.spotify.com/v1/artists/5eAWCfyUhZtHHtBdNk56l1"
    },
    {
      "initialPoolSize": 250,
      "afterFilteringSize": 2,
      "afterRelinkingSize": 2,
      "id": "7oPftvlwr6VrsViSDV7fJY",
      "type": "ARTIST",
      "href": "https://api.spotify.com/v1/artists/7oPftvlwr6VrsViSDV7fJY"
    }
  ]
}